ftx/__init__.py
ftx/ftx.py
huobi/__init__.py
huobi/huobi.py
hft_api-0.1.1.dist-info/METADATA
hft_api-0.1.1.dist-info/WHEEL
hft_api-0.1.1.dist-info/top_level.txt
hft_api-0.1.1.dist-info/RECORD
