Metadata-Version: 2.1
Name: hft-api
Version: 0.1.1
Summary: Api of hft
Home-page: https://htf_api.readthedocs.io/
Author: Olim Nizomov, Nodirbek O'ktamov
Author-email: olimbek.nizomov@mail.ru
License: MIT
Platform: UNKNOWN
Classifier: Intended Audience :: Developers
Classifier: License :: OSI Approved :: MIT License
Classifier: Programming Language :: Python
Classifier: Programming Language :: Python :: 3
Classifier: Programming Language :: Python :: 3.6
Classifier: Programming Language :: Python :: 3.7
Classifier: Programming Language :: Python :: 3.8
Classifier: Programming Language :: Python :: 3.9
Classifier: Operating System :: OS Independent
Requires-Dist: requests
